LICENSE.txt
MANIFEST.in
README.txt
setup.py
lfs_sofortueberweisung/__init__.py
lfs_sofortueberweisung/views.py
lfs_sofortueberweisung.egg-info/PKG-INFO
lfs_sofortueberweisung.egg-info/SOURCES.txt
lfs_sofortueberweisung.egg-info/dependency_links.txt
lfs_sofortueberweisung.egg-info/not-zip-safe
lfs_sofortueberweisung.egg-info/requires.txt
lfs_sofortueberweisung.egg-info/top_level.txt