Metadata-Version: 1.0
Name: lfs-sofortueberweisung
Version: 1.0b1
Summary: sofortueberweisung.de for LFS
Home-page: http://www.getlfs.com
Author: Kai Diefenbach
Author-email: kai.diefenbach@iqpp.de
License: BSD
Keywords: django e-commerce online-shop
Platform: UNKNOWN
Classifier: Environment :: Web Environment
Classifier: Framework :: Django
Classifier: License :: OSI Approved :: BSD License
Classifier: Operating System :: OS Independent
Classifier: Programming Language :: Python
